incomepropertyevaluatorkit/__init__.py
py_incomepropertyevaluatorkit-0.0.1.dist-info/DESCRIPTION.rst
py_incomepropertyevaluatorkit-0.0.1.dist-info/METADATA
py_incomepropertyevaluatorkit-0.0.1.dist-info/RECORD
py_incomepropertyevaluatorkit-0.0.1.dist-info/WHEEL
py_incomepropertyevaluatorkit-0.0.1.dist-info/metadata.json
py_incomepropertyevaluatorkit-0.0.1.dist-info/top_level.txt
