Metadata-Version: 2.0
Name: py-incomepropertyevaluatorkit
Version: 0.0.1
Summary: Python library for performing rental and income property calculations.
Home-page: https://github.com/MikaSoftware/incomepropertyevaluatorkit-py
Author: Bartlomiej Mika
Author-email: bart@mikasoftware.com
License: BSD 2-Clause License
Keywords: mortgage real estate financial business bank
Platform: UNKNOWN
Classifier: Development Status :: 1 - Planning
Classifier: Intended Audience :: Education
Classifier: License :: OSI Approved :: BSD License
Classifier: Natural Language :: English
Classifier: Programming Language :: Python :: 3.6
Classifier: Topic :: Office/Business :: Financial :: Accounting
Requires-Python: >=3.6
Requires-Dist: py-moneyed
Requires-Dist: py-mortgagekit
Requires-Dist: numpy
Requires-Dist: pisa
Requires-Dist: xhtml2pdf (>=0.2b1)
